{"N1vbNjdAhk7+U0wUGGxRyg==":"mbr-90x92.png","LmE3PFi0kc3Sh647o9r6wA==":"img-4060-1456x1456.jpg","Xrt8AzD0OhXYJOscsIMjHw==":"img-4534-900x900.jpg","E0KdVTnsyXQ9dENrP6iTZw==":"img-4534-900x900.jpeg","CwUiYOUjzpkR2ZCkUbNKxA==":"img-4558-900x900.jpg","WzLNVy+UHcnu2rUhqOXUgg==":"img-4504-900x900.jpeg","fxGM8k770i3KpLPtQjPuwA==":"img-4505-900x900.jpeg","Cb1MOlP+v4FSYY/fzfMVNw==":"img-4506-900x900.jpeg","fEfl8s4leDxrf2Xq+YauRA==":"img-4507-900x900.jpeg","QKBsOP0czybsTwlNuBM6CQ==":"img-4261-900x900.jpg","BmqClVaGXS90iS41H/thAQ==":"922fd8bc-b825-4060-a37f-57c7a9242a17-900x506.jpeg","7zdeE/Rbj8U5DPUjZwmLbQ==":"img-4013-2000x2000.jpg","0tuDnmBSxjmiw/LXvmKNkA==":"mbr-1920x1281.jpg","mNueeyUETPTdSJolvj3uMA==":"mbr-1920x1080.jpg","3+tF8eX8ZzyUC7WVs0og4g==":"img-6474-2000x1137.jpg","Iu0PMnxnr1Cq4ZT1imfoIA==":"%D0%A1%D0%BD%D0%B8%D0%BC%D0%BE%D0%BA%20%D1%8D%D0%BA%D1%80%D0%B0%D0%BD%D0%B0%202020-05-20%20%D0%B2%2020.54.05-2054x1498.png","+sWccizi8Kopb32fU3H9NQ==":"%D0%A1%D0%BD%D0%B8%D0%BC%D0%BE%D0%BA%20%D1%8D%D0%BA%D1%80%D0%B0%D0%BD%D0%B0%202020-05-20%20%D0%B2%2020.54.51-2048x1500.png","ukp0X2oRe5DBqTDFTrQyTg==":"%D0%A1%D0%BD%D0%B8%D0%BC%D0%BE%D0%BA%20%D1%8D%D0%BA%D1%80%D0%B0%D0%BD%D0%B0%202020-05-20%20%D0%B2%2020.55.40-2054x1502.png","+95tlgWEUfL/+AQQrRnbkQ==":"%D0%A1%D0%BD%D0%B8%D0%BC%D0%BE%D0%BA%20%D1%8D%D0%BA%D1%80%D0%B0%D0%BD%D0%B0%202020-05-20%20%D0%B2%2020.56.15-2052x1506.png","8XXU7qRghMWwowdcCGdgZg==":"%D0%A1%D0%BD%D0%B8%D0%BC%D0%BE%D0%BA%20%D1%8D%D0%BA%D1%80%D0%B0%D0%BD%D0%B0%202020-05-20%20%D0%B2%2020.56.48-2040x1518.png","THWPpg+9KCaX10r3dQPfUQ==":"img-3971-2000x2000.jpg","qG/nMCoKIBKxU9Mw6o2Q/g==":"img-3971-2000x2000.jpeg","3xBJGiHdA/CEKtKwexqnJw==":"img-4475-1462x1462.jpg","ChJF5/5xiA9sr3GnHs2kuw==":"mbr-1920x1440.jpg","S01+hLiomkxfJoxDxUpwdw==":"%D0%A1%D0%BD%D0%B8%D0%BC%D0%BE%D0%BA%20%D1%8D%D0%BA%D1%80%D0%B0%D0%BD%D0%B0%202020-05-20%20%D0%B2%2021.14.12-876x542.png","whvlHqAgYh/wnd3Vf70+PQ==":"%D0%A1%D0%BD%D0%B8%D0%BC%D0%BE%D0%BA%20%D1%8D%D0%BA%D1%80%D0%B0%D0%BD%D0%B0%202020-05-20%20%D0%B2%2021.17.22-1044x1246.png","m8CK8L7p50Djdm46cquLcw==":"img-4238-506x506.jpg","d4MsVfX5dQX0quF3YlT0PA==":"background3.jpg"}